main.py
hellofromsean-0.1.2.dist-info/METADATA
hellofromsean-0.1.2.dist-info/WHEEL
hellofromsean-0.1.2.dist-info/top_level.txt
hellofromsean-0.1.2.dist-info/RECORD
