Metadata-Version: 2.2
Name: hellofromsean
Version: 0.1.2
Summary: Just a regular greeting i guess?
Requires-Python: >=3.13
